[
    {
        "layout_dets": [
            {
                "category_id": 2,
                "poly": [
                    756.5902099609375,
                    2175.733642578125,
                    897.653076171875,
                    2175.733642578125,
                    897.653076171875,
                    2219.9384765625,
                    756.5902099609375,
                    2219.9384765625
                ],
                "score": 0.999944806098938
            },
            {
                "category_id": 1,
                "poly": [
                    257.8372802734375,
                    1801.7989501953125,
                    1402.7435302734375,
                    1801.7989501953125,
                    1402.7435302734375,
                    1902.80322265625,
                    257.8372802734375,
                    1902.80322265625
                ],
                "score": 0.9927989840507507
            },
            {
                "category_id": 1,
                "poly": [
                    257.3520812988281,
                    1369.8900146484375,
                    779.4403686523438,
                    1369.8900146484375,
                    779.4403686523438,
                    1405.848388671875,
                    257.3520812988281,
                    1405.848388671875
                ],
                "score": 0.9822698831558228
            },
            {
                "category_id": 1,
                "poly": [
                    259.4501647949219,
                    1521.2757568359375,
                    600.1932373046875,
                    1521.2757568359375,
                    600.1932373046875,
                    1555.731689453125,
                    259.4501647949219,
                    1555.731689453125
                ],
                "score": 0.9158017039299011
            },
            {
                "category_id": 5,
                "poly": [
                    240.87689208984375,
                    238.4110107421875,
                    1423.214111328125,
                    238.4110107421875,
                    1423.214111328125,
                    2018.2242431640625,
                    240.87689208984375,
                    2018.2242431640625
                ],
                "score": 0.9145997762680054,
                "html": "<html><body><table><tr><td rowspan=\"2\">第01部分 SOP标题</td><td>流程名称</td><td>流程编号</td><td>版本号</td></tr><tr><td>维谛模块化UPS单机下电关机 操作流程标准（SOP)</td><td>SD-YJD-UPS-03</td><td>V1.0</td></tr><tr><td rowspan=\"2\">第02部分 现场信息</td><td>基地名称</td><td>适用范围</td><td>专业负责人</td></tr><tr><td>云计算基地</td><td>A2机楼</td><td>赵玲玲</td></tr><tr><td rowspan=\"3\">第03部分 设备信息</td><td>设备厂家</td><td>设备名称</td><td>设备型号 Liebert EPM</td></tr><tr><td>维谛</td><td>不间断供电系统</td><td>0400kTK16FN0100 0</td></tr><tr><td>负责人电话</td><td>售后联系电话</td><td>设备厂家技术支 持电话 13210093575</td></tr><tr><td>第04部分</td><td colspan=\"3\">刘晓辉 13210093575 执行本标准操作流程的原因</td></tr><tr><td colspan=\"4\">为指导UPS单机下电关机操作，特制定此规程（此操作所有电源开关、隔离开关和断路 器均断开，UPS不再给负载供电。）。</td></tr><tr><td>第05部分 1.现场操作应2人，一人操作，另一人监护；</td><td colspan=\"3\">本标准操作流程的安全要求</td></tr><tr><td colspan=\"4\">2.准备好绝缘手套、绝缘靴及安全帽等；</td></tr><tr><td colspan=\"4\">第06部分 本标准操作流程的各种风险</td></tr><tr><td colspan=\"4\">1.误操作，导致设备掉电; 2.人身触电风险；</td></tr><tr><td colspan=\"4\">第07部分 本标准操作流程所需各项检查及准备工作、仪器仪表及耗材</td></tr><tr><td colspan=\"4\">1.提前准备操作过程中所使用的工具：低压绝缘手套、安全帽等。 2.安装、操作和维护过程中必须使用专用的防护用具，如佩戴低压绝缘手套，佩戴护目镜、 穿安全服、戴安全帽、穿安全鞋等。</td></tr><tr><td colspan=\"4\">第8部分 本标准操作流程执行后所做的检查工作</td></tr></table></body></html>"
            },
            {
                "category_id": 1,
                "poly": [
                    260.426025390625,
                    1735.6328125,
                    1097.5494384765625,
                    1735.6328125,
                    1097.5494384765625,
                    1772.0311279296875,
                    260.426025390625,
                    1772.0311279296875
                ],
                "score": 0.5778173804283142
            },
            {
                "category_id": 1,
                "poly": [
                    257.7781066894531,
                    1304.4432373046875,
                    835.1480712890625,
                    1304.4432373046875,
                    835.1480712890625,
                    1342.8363037109375,
                    257.7781066894531,
                    1342.8363037109375
                ],
                "score": 0.347517728805542
            },
            {
                "category_id": 13,
                "poly": [
                    277,
                    335,
                    330,
                    335,
                    330,
                    370,
                    277,
                    370
                ],
                "score": 0.33,
                "latex": "\\textcircled{5}\\textcircled{1}\\textcircled{2}"
            },
            {
                "category_id": 15,
                "poly": [
                    756.0,
                    2176.0,
                    896.0,
                    2176.0,
                    896.0,
                    2223.0,
                    756.0,
                    2223.0
                ],
                "score": 1.0,
                "text": ""
            },
            {
                "category_id": 15,
                "poly": [
                    264.0,
                    1808.0,
                    1395.0,
                    1808.0,
                    1395.0,
                    1839.0,
                    264.0,
                    1839.0
                ],
                "score": 1.0,
                "text": ""
            },
            {
                "category_id": 15,
                "poly": [
                    265.0,
                    1870.0,
                    715.0,
                    1870.0,
                    715.0,
                    1906.0,
                    265.0,
                    1906.0
                ],
                "score": 1.0,
                "text": ""
            },
            {
                "category_id": 15,
                "poly": [
                    265.0,
                    1374.0,
                    771.0,
                    1374.0,
                    771.0,
                    1404.0,
                    265.0,
                    1404.0
                ],
                "score": 1.0,
                "text": ""
            },
            {
                "category_id": 15,
                "poly": [
                    266.0,
                    1525.0,
                    595.0,
                    1525.0,
                    595.0,
                    1555.0,
                    266.0,
                    1555.0
                ],
                "score": 1.0,
                "text": ""
            },
            {
                "category_id": 15,
                "poly": [
                    266.0,
                    1742.0,
                    1096.0,
                    1742.0,
                    1096.0,
                    1772.0,
                    266.0,
                    1772.0
                ],
                "score": 1.0,
                "text": ""
            },
            {
                "category_id": 15,
                "poly": [
                    267.0,
                    1310.0,
                    829.0,
                    1310.0,
                    829.0,
                    1340.0,
                    267.0,
                    1340.0
                ],
                "score": 1.0,
                "text": ""
            }
        ],
        "page_info": {
            "page_no": 0,
            "height": 2339,
            "width": 1654
        }
    },
    {
        "layout_dets": [
            {
                "category_id": 2,
                "poly": [
                    755.4478149414062,
                    2176.482421875,
                    896.3242797851562,
                    2176.482421875,
                    896.3242797851562,
                    2220.9921875,
                    755.4478149414062,
                    2220.9921875
                ],
                "score": 0.9999970197677612
            },
            {
                "category_id": 0,
                "poly": [
                    260.5596008300781,
                    1868.6051025390625,
                    617.9898071289062,
                    1868.6051025390625,
                    617.9898071289062,
                    1918.5361328125,
                    260.5596008300781,
                    1918.5361328125
                ],
                "score": 0.9999916553497314
            },
            {
                "category_id": 1,
                "poly": [
                    259.4131774902344,
                    309.10980224609375,
                    946.1903686523438,
                    309.10980224609375,
                    946.1903686523438,
                    346.4418029785156,
                    259.4131774902344,
                    346.4418029785156
                ],
                "score": 0.9999828338623047
            },
            {
                "category_id": 3,
                "poly": [
                    848.1959838867188,
                    1013.5380859375,
                    1408.498779296875,
                    1013.5380859375,
                    1408.498779296875,
                    1343.8348388671875,
                    848.1959838867188,
                    1343.8348388671875
                ],
                "score": 0.9999669790267944
            },
            {
                "category_id": 1,
                "poly": [
                    262.26507568359375,
                    246.001220703125,
                    573.7409057617188,
                    246.001220703125,
                    573.7409057617188,
                    280.103515625,
                    262.26507568359375,
                    280.103515625
                ],
                "score": 0.9999663829803467
            },
            {
                "category_id": 3,
                "poly": [
                    850.1642456054688,
                    1489.457275390625,
                    1408.5611572265625,
                    1489.457275390625,
                    1408.5611572265625,
                    1651.0916748046875,
                    850.1642456054688,
                    1651.0916748046875
                ],
                "score": 0.9998206496238708
            },
            {
                "category_id": 1,
                "poly": [
                    853.7576293945312,
                    1365.1116943359375,
                    1395.8033447265625,
                    1365.1116943359375,
                    1395.8033447265625,
                    1471.5714111328125,
                    853.7576293945312,
                    1471.5714111328125
                ],
                "score": 0.9997713565826416
            },
            {
                "category_id": 1,
                "poly": [
                    856.3565673828125,
                    760.4915161132812,
                    1170.5782470703125,
                    760.4915161132812,
                    1170.5782470703125,
                    798.417236328125,
                    856.3565673828125,
                    798.417236328125
                ],
                "score": 0.9948148131370544
            },
            {
                "category_id": 1,
                "poly": [
                    851.2815551757812,
                    818.8153686523438,
                    1398.5477294921875,
                    818.8153686523438,
                    1398.5477294921875,
                    931.569091796875,
                    851.2815551757812,
                    931.569091796875
                ],
                "score": 0.9652408361434937
            },
            {
                "category_id": 1,
                "poly": [
                    850.7987670898438,
                    1797.42431640625,
                    1393.5185546875,
                    1797.42431640625,
                    1393.5185546875,
                    1906.25732421875,
                    850.7987670898438,
                    1906.25732421875
                ],
                "score": 0.9639572501182556
            },
            {
                "category_id": 5,
                "poly": [
                    247.7215118408203,
                    427.9661865234375,
                    1410.3843994140625,
                    427.9661865234375,
                    1410.3843994140625,
                    746.8081665039062,
                    247.7215118408203,
                    746.8081665039062
                ],
                "score": 0.929571270942688,
                "html": "<html><body><table><tr><td>第9部分</td><td colspan=\"3\">本标准操作流程的批准</td></tr><tr><td rowspan=\"2\">起草</td><td>起草人姓名</td><td>起草人职务</td><td>起草日期</td></tr><tr><td>赵玲玲</td><td>维护工程师</td><td>2024年2月20日</td></tr><tr><td rowspan=\"2\">审核</td><td>审核人姓名</td><td>审核人职务</td><td>审核日期</td></tr><tr><td>叶笑鸣</td><td>维护工程师</td><td>2024年3月20日</td></tr><tr><td rowspan=\"2\">批准</td><td>批准人姓名</td><td>批准人职务</td><td>批准日期</td></tr><tr><td>赵明</td><td>运维部主任</td><td>2024年3月20日</td></tr></table></body></html>"
            },
            {
                "category_id": 0,
                "poly": [
                    256.5252990722656,
                    829.2168579101562,
                    829.9678344726562,
                    829.2168579101562,
                    829.9678344726562,
                    966.2509765625,
                    256.5252990722656,
                    966.2509765625
                ],
                "score": 0.8796695470809937
            },
            {
                "category_id": 1,
                "poly": [
                    256.6441345214844,
                    829.3389892578125,
                    829.7754516601562,
                    829.3389892578125,
                    829.7754516601562,
                    966.3480224609375,
                    256.6441345214844,
                    966.3480224609375
                ],
                "score": 0.43464553356170654
            },
            {
                "category_id": 15,
                "poly": [
                    756.0,
                    2175.0,
                    896.0,
                    2175.0,
                    896.0,
                    2223.0,
                    756.0,
                    2223.0
                ],
                "score": 1.0,
                "text": ""
            },
            {
                "category_id": 15,
                "poly": [
                    265.0,
                    1874.0,
                    612.0,
                    1874.0,
                    612.0,
                    1918.0,
                    265.0,
                    1918.0
                ],
                "score": 1.0,
                "text": ""
            },
            {
                "category_id": 15,
                "poly": [
                    265.0,
                    315.0,
                    941.0,
                    315.0,
                    941.0,
                    345.0,
                    265.0,
                    345.0
                ],
                "score": 1.0,
                "text": ""
            },
            {
                "category_id": 15,
                "poly": [
                    265.0,
                    247.0,
                    567.0,
                    247.0,
                    567.0,
                    280.0,
                    265.0,
                    280.0
                ],
                "score": 1.0,
                "text": ""
            },
            {
                "category_id": 15,
                "poly": [
                    856.0,
                    1369.0,
                    1390.0,
                    1369.0,
                    1390.0,
                    1402.0,
                    856.0,
                    1402.0
                ],
                "score": 1.0,
                "text": ""
            },
            {
                "category_id": 15,
                "poly": [
                    855.0,
                    1432.0,
                    1303.0,
                    1432.0,
                    1303.0,
                    1468.0,
                    855.0,
                    1468.0
                ],
                "score": 1.0,
                "text": ""
            },
            {
                "category_id": 15,
                "poly": [
                    856.0,
                    762.0,
                    1167.0,
                    762.0,
                    1167.0,
                    796.0,
                    856.0,
                    796.0
                ],
                "score": 1.0,
                "text": ""
            },
            {
                "category_id": 15,
                "poly": [
                    857.0,
                    828.0,
                    1394.0,
                    828.0,
                    1394.0,
                    860.0,
                    857.0,
                    860.0
                ],
                "score": 1.0,
                "text": ""
            },
            {
                "category_id": 15,
                "poly": [
                    853.0,
                    888.0,
                    974.0,
                    888.0,
                    974.0,
                    932.0,
                    853.0,
                    932.0
                ],
                "score": 1.0,
                "text": ""
            },
            {
                "category_id": 15,
                "poly": [
                    856.0,
                    1802.0,
                    1386.0,
                    1802.0,
                    1386.0,
                    1835.0,
                    856.0,
                    1835.0
                ],
                "score": 1.0,
                "text": ""
            },
            {
                "category_id": 15,
                "poly": [
                    857.0,
                    1867.0,
                    1202.0,
                    1867.0,
                    1202.0,
                    1900.0,
                    857.0,
                    1900.0
                ],
                "score": 1.0,
                "text": ""
            },
            {
                "category_id": 15,
                "poly": [
                    264.0,
                    836.0,
                    826.0,
                    836.0,
                    826.0,
                    877.0,
                    264.0,
                    877.0
                ],
                "score": 1.0,
                "text": ""
            },
            {
                "category_id": 15,
                "poly": [
                    260.0,
                    917.0,
                    364.0,
                    917.0,
                    364.0,
                    971.0,
                    260.0,
                    971.0
                ],
                "score": 1.0,
                "text": ""
            },
            {
                "category_id": 15,
                "poly": [
                    264.0,
                    836.0,
                    826.0,
                    836.0,
                    826.0,
                    877.0,
                    264.0,
                    877.0
                ],
                "score": 1.0,
                "text": ""
            },
            {
                "category_id": 15,
                "poly": [
                    260.0,
                    917.0,
                    364.0,
                    917.0,
                    364.0,
                    971.0,
                    260.0,
                    971.0
                ],
                "score": 1.0,
                "text": ""
            }
        ],
        "page_info": {
            "page_no": 1,
            "height": 2339,
            "width": 1654
        }
    },
    {
        "layout_dets": [
            {
                "category_id": 2,
                "poly": [
                    755.6262817382812,
                    2177.563232421875,
                    895.5323486328125,
                    2177.563232421875,
                    895.5323486328125,
                    2220.087158203125,
                    755.6262817382812,
                    2220.087158203125
                ],
                "score": 0.9999935030937195
            },
            {
                "category_id": 0,
                "poly": [
                    260.1601257324219,
                    741.2081298828125,
                    672.5498657226562,
                    741.2081298828125,
                    672.5498657226562,
                    793.0602416992188,
                    260.1601257324219,
                    793.0602416992188
                ],
                "score": 0.9999918937683105
            },
            {
                "category_id": 3,
                "poly": [
                    849.5360717773438,
                    205.78897094726562,
                    1409.6978759765625,
                    205.78897094726562,
                    1409.6978759765625,
                    535.4722290039062,
                    849.5360717773438,
                    535.4722290039062
                ],
                "score": 0.9999796748161316
            },
            {
                "category_id": 3,
                "poly": [
                    849.3436889648438,
                    941.0068359375,
                    1377.7410888671875,
                    941.0068359375,
                    1377.7410888671875,
                    1494.674560546875,
                    849.3436889648438,
                    1494.674560546875
                ],
                "score": 0.9999749064445496
            },
            {
                "category_id": 3,
                "poly": [
                    853.5105590820312,
                    1770.229736328125,
                    1410.52392578125,
                    1770.229736328125,
                    1410.52392578125,
                    2056.053466796875,
                    853.5105590820312,
                    2056.053466796875
                ],
                "score": 0.9998735785484314
            },
            {
                "category_id": 1,
                "poly": [
                    853.1439819335938,
                    1578.898193359375,
                    1400.91064453125,
                    1578.898193359375,
                    1400.91064453125,
                    1751.405029296875,
                    853.1439819335938,
                    1751.405029296875
                ],
                "score": 0.9992613196372986
            },
            {
                "category_id": 1,
                "poly": [
                    850.234375,
                    688.7880249023438,
                    1401.856689453125,
                    688.7880249023438,
                    1401.856689453125,
                    924.5547485351562,
                    850.234375,
                    924.5547485351562
                ],
                "score": 0.9990248084068298
            },
            {
                "category_id": 0,
                "poly": [
                    257.0158386230469,
                    1690.50927734375,
                    830.3033447265625,
                    1690.50927734375,
                    830.3033447265625,
                    1834.4041748046875,
                    257.0158386230469,
                    1834.4041748046875
                ],
                "score": 0.9984795451164246
            },
            {
                "category_id": 15,
                "poly": [
                    757.0,
                    2175.0,
                    897.0,
                    2175.0,
                    897.0,
                    2223.0,
                    757.0,
                    2223.0
                ],
                "score": 1.0,
                "text": ""
            },
            {
                "category_id": 15,
                "poly": [
                    264.0,
                    745.0,
                    671.0,
                    745.0,
                    671.0,
                    790.0,
                    264.0,
                    790.0
                ],
                "score": 1.0,
                "text": ""
            },
            {
                "category_id": 15,
                "poly": [
                    857.0,
                    1585.0,
                    1394.0,
                    1585.0,
                    1394.0,
                    1617.0,
                    857.0,
                    1617.0
                ],
                "score": 1.0,
                "text": ""
            },
            {
                "category_id": 15,
                "poly": [
                    857.0,
                    1649.0,
                    1395.0,
                    1649.0,
                    1395.0,
                    1683.0,
                    857.0,
                    1683.0
                ],
                "score": 1.0,
                "text": ""
            },
            {
                "category_id": 15,
                "poly": [
                    858.0,
                    1713.0,
                    1130.0,
                    1713.0,
                    1130.0,
                    1749.0,
                    858.0,
                    1749.0
                ],
                "score": 1.0,
                "text": ""
            },
            {
                "category_id": 15,
                "poly": [
                    855.0,
                    694.0,
                    1397.0,
                    694.0,
                    1397.0,
                    729.0,
                    855.0,
                    729.0
                ],
                "score": 1.0,
                "text": ""
            },
            {
                "category_id": 15,
                "poly": [
                    855.0,
                    757.0,
                    1088.0,
                    757.0,
                    1088.0,
                    797.0,
                    855.0,
                    797.0
                ],
                "score": 1.0,
                "text": ""
            },
            {
                "category_id": 15,
                "poly": [
                    854.0,
                    824.0,
                    1397.0,
                    824.0,
                    1397.0,
                    860.0,
                    854.0,
                    860.0
                ],
                "score": 1.0,
                "text": ""
            },
            {
                "category_id": 15,
                "poly": [
                    856.0,
                    888.0,
                    1121.0,
                    888.0,
                    1121.0,
                    925.0,
                    856.0,
                    925.0
                ],
                "score": 1.0,
                "text": ""
            },
            {
                "category_id": 15,
                "poly": [
                    265.0,
                    1700.0,
                    827.0,
                    1700.0,
                    827.0,
                    1742.0,
                    265.0,
                    1742.0
                ],
                "score": 1.0,
                "text": ""
            },
            {
                "category_id": 15,
                "poly": [
                    265.0,
                    1787.0,
                    783.0,
                    1787.0,
                    783.0,
                    1829.0,
                    265.0,
                    1829.0
                ],
                "score": 1.0,
                "text": ""
            }
        ],
        "page_info": {
            "page_no": 2,
            "height": 2339,
            "width": 1654
        }
    },
    {
        "layout_dets": [
            {
                "category_id": 2,
                "poly": [
                    757.029541015625,
                    2176.742919921875,
                    894.895751953125,
                    2176.742919921875,
                    894.895751953125,
                    2219.365478515625,
                    757.029541015625,
                    2219.365478515625
                ],
                "score": 0.9999908804893494
            },
            {
                "category_id": 3,
                "poly": [
                    247.1983184814453,
                    189.42437744140625,
                    1414.8485107421875,
                    189.42437744140625,
                    1414.8485107421875,
                    1054.684814453125,
                    247.1983184814453,
                    1054.684814453125
                ],
                "score": 0.9267956614494324
            },
            {
                "category_id": 5,
                "poly": [
                    245.49954223632812,
                    188.72032165527344,
                    1411.532470703125,
                    188.72032165527344,
                    1411.532470703125,
                    1054.1815185546875,
                    245.49954223632812,
                    1054.1815185546875
                ],
                "score": 0.36065012216567993,
                "html": "<html><body><table><tr><td rowspan=\"2\"></td><td>Q2 旁路/BIB</td></tr><tr><td>Q5 输出/MIB</td></tr><tr><td></td><td></td></tr></table></body></html>"
            },
            {
                "category_id": 15,
                "poly": [
                    755.0,
                    2175.0,
                    899.0,
                    2175.0,
                    899.0,
                    2223.0,
                    755.0,
                    2223.0
                ],
                "score": 1.0,
                "text": ""
            }
        ],
        "page_info": {
            "page_no": 3,
            "height": 2339,
            "width": 1654
        }
    }
]